wyvern/__init__.py
wyvern/__main__.py
wyvern/_internals.py
wyvern/_types.py
wyvern/aliases.py
wyvern/clients.py
wyvern/colors.py
wyvern/commands/__init__.py
wyvern/commands/base.py
wyvern/commands/command_handler.py
wyvern/commands/context_menus.py
wyvern/commands/slash_commands.py
wyvern/components/__init__.py
wyvern/components/base.py
wyvern/components/buttons.py
wyvern/components/container.py
wyvern/components/modals.py
wyvern/components/selects.py
wyvern/constructors/__init__.py
wyvern/constructors/components.py
wyvern/constructors/embeds.py
wyvern/events.py
wyvern/exceptions.py
wyvern/extensions/__init__.py
wyvern/extensions/tasks.py
wyvern/files.py
wyvern/gateway/__init__.py
wyvern/gateway/enums.py
wyvern/gateway/keep_alive.py
wyvern/intents.py
wyvern/interactions/__init__.py
wyvern/interactions/_converters.py
wyvern/interactions/applications.py
wyvern/interactions/base.py
wyvern/interactions/components.py
wyvern/interactions/localizations.py
wyvern/models/__init__.py
wyvern/models/_converters.py
wyvern/models/base.py
wyvern/models/channels.py
wyvern/models/emojis.py
wyvern/models/guilds.py
wyvern/models/members.py
wyvern/models/messages.py
wyvern/models/roles.py
wyvern/models/stickers.py
wyvern/models/users.py
wyvern/models/voices.py
wyvern/permissions.py
wyvern/plugins.py
wyvern/presences.py
wyvern/py.typed
wyvern/rest/__init__.py
wyvern/rest/endpoints.py
wyvern/state_handlers/__init__.py
wyvern/state_handlers/members.py
wyvern/state_handlers/users.py
wyvern/utils.py
wyvern/ux.py
wyvern-0.1.1.dist-info/LICENSE
wyvern-0.1.1.dist-info/WHEEL
wyvern-0.1.1.dist-info/METADATA
wyvern-0.1.1.dist-info/RECORD
