Metadata-Version: 2.1
Name: wyvern
Version: 0.1.1
Summary: A flexible and easy to use Discord API wrapper for python 🚀.
License: MIT
Author: sarthhh
Requires-Python: >=3.8,<4.0
Classifier: License :: OSI Approved :: MIT License
Classifier: Programming Language :: Python :: 3
Classifier: Programming Language :: Python :: 3.8
Classifier: Programming Language :: Python :: 3.9
Classifier: Programming Language :: Python :: 3.10
Classifier: Programming Language :: Python :: 3.11
Requires-Dist: aiohttp (>=3.8.1,<4.0.0)
Requires-Dist: attrs (>=22.1.0,<23.0.0)
Requires-Dist: colorama (>=0.4.6,<0.5.0)
